{
  "name": "CIC",
  "children": [
    {
      "name": "公开市场股票总组合",
      "children": [
        {
          "name": "全球股票",
          "children": [
            {
              "name": "股权投资部",
              "children":[
                {
                  "name":"委托投资",
                  "children": [
                    { "name": "全球积极型产品" }
                  ],
                  "dependsOn": ["公开市场股票总组合","股权投资部","全球股票"]
                  }
              ],
              "dependsOn": ["公开市场股票总组合","全球股票"]
            }
          ]
        }
      ]
    }
  ]
}
